[
	{
		"name": "Federation of United Planets",
		"leaderName": "James.T.Kirk",
		"adjective": ["federal"],
		"startBias": ["Snow"],
		"preferredVictoryType": "Scientific",
		
		"startIntroPart1": "Live Long and Prosper",
		"startIntroPart2": "The United Federation of Planets is an alliance of species dedicated to space exploration.  It was founded by Vulcans, Humans, Andorians, and Tellarites in 2161. The Federation has since expanded to include many other members and continues to grow in size, influence, and importance throughout the galaxy.",
		
		"declaringWar": "Don't leave us any Logical solution",
		"attacked": "The Federation is committed to defending its members from all attackers",
		"defeated": "Change is the essential process of all existence, Live Long and Prosper",
		"introduction": "We come in peace! Live Long and Prosper",
		
		"neutralHello": "How are you doing?",
		"neutralLetsHearIt": ["Go on.","What do you say?","You may begin."],
		"neutralNo": ["It's highly illogical"],
		"neutralYes": ["It's logical"],

		"hateHello": "What do you want now?",
		"hateLetsHearIt": ["Speak!","What do you say?","Go on."],
		"hateNo": ["That is not possible!","It's highly illogical"],
		"hateYes": ["It's logical"],
		
		"afterPeace": "Let's hope this peace lasts a long time, Live Long and Prosper",
		"tradeRequest": "We think you may be interested in this trade offer.",

		"outerColor": [16,16,16],
		"innerColor": [255,200,200],
		"unique": "MANIFEST_DESTINY",
		"cities": ["Sol","Vulcano","Andoria","Tellar","Betazed","Trill","Deneb","Babel","Alpha Centauri",
			"P'Jem","Wolf 359","Sirio","Vega","Memory Alpha","Tau Ceti","Terra Nova","Archer","Lorillia","Denobula Triaxa",
			"Bernard's Star","Orai-12","","Altair","Gemet","Doska","Prya","Aruna","Earorfiliad","Achillon",
			"Noakyn","Thama","Axanar","Aiti","Groombridge 34","Final Frontier"]
	}
]
